.gitignore
.travis.yml
MANIFEST.in
README.rst
README.txt
bootstrap.py
buildout.cfg
setup.cfg
setup.py
travis.cfg
docs/CREDITS.txt
docs/HISTORY.txt
docs/INSTALL.txt
docs/LICENSE.GPL
docs/LICENSE.txt
parts/omelette/collective/prettydate/__init__.py
parts/omelette/collective/prettydate/config.py
parts/omelette/collective/prettydate/configure.zcml
parts/omelette/collective/prettydate/interfaces.py
parts/omelette/collective/prettydate/testing.py
parts/omelette/collective/prettydate/utility.py
parts/omelette/collective/prettydate/locales/collective.prettydate.pot
parts/omelette/collective/prettydate/locales/de/LC_MESSAGES/collective.prettydate.po
parts/omelette/collective/prettydate/locales/es/LC_MESSAGES/collective.prettydate.po
parts/omelette/collective/prettydate/locales/fi_FI/LC_MESSAGES/collective.prettydate.po
parts/omelette/collective/prettydate/locales/it/LC_MESSAGES/collective.prettydate.po
parts/omelette/collective/prettydate/locales/pt_BR/LC_MESSAGES/collective.prettydate.po
parts/omelette/collective/prettydate/tests/__init__.py
parts/omelette/collective/prettydate/tests/test_utility.py
src/collective/__init__.py
src/collective.prettydate.egg-info/PKG-INFO
src/collective.prettydate.egg-info/SOURCES.txt
src/collective.prettydate.egg-info/dependency_links.txt
src/collective.prettydate.egg-info/entry_points.txt
src/collective.prettydate.egg-info/namespace_packages.txt
src/collective.prettydate.egg-info/not-zip-safe
src/collective.prettydate.egg-info/requires.txt
src/collective.prettydate.egg-info/top_level.txt
src/collective/prettydate/__init__.py
src/collective/prettydate/config.py
src/collective/prettydate/configure.zcml
src/collective/prettydate/interfaces.py
src/collective/prettydate/testing.py
src/collective/prettydate/utility.py
src/collective/prettydate/locales/collective.prettydate.pot
src/collective/prettydate/locales/de/LC_MESSAGES/collective.prettydate.po
src/collective/prettydate/locales/es/LC_MESSAGES/collective.prettydate.mo
src/collective/prettydate/locales/es/LC_MESSAGES/collective.prettydate.po
src/collective/prettydate/locales/fi_FI/LC_MESSAGES/collective.prettydate.po
src/collective/prettydate/locales/it/LC_MESSAGES/collective.prettydate.po
src/collective/prettydate/locales/pt_BR/LC_MESSAGES/collective.prettydate.mo
src/collective/prettydate/locales/pt_BR/LC_MESSAGES/collective.prettydate.po
src/collective/prettydate/tests/__init__.py
