Metadata-Version: 1.1
Name: collective.prettydate
Version: 1.2.1
Summary: Represents a date on a relative format so, instead of '01/02/2012', it would be displayed as '4 hours ago', 'yesterday' or 'last week', which is easier to read and understand for most people.
Home-page: https://github.com/collective/collective.prettydate
Author: Franco Pellegrini
Author-email: frapell@gmail.com
License: UNKNOWN
Keywords: plone prettydate datetime
Platform: UNKNOWN
Classifier: Development Status :: 5 - Production/Stable
Classifier: Framework :: Plone
Classifier: Framework :: Plone :: 4.0
Classifier: Framework :: Plone :: 4.1
Classifier: Framework :: Plone :: 4.2
Classifier: Framework :: Plone :: 4.3
Classifier: Framework :: Plone :: 5.0
Classifier: Intended Audience :: Developers
Classifier: License :: OSI Approved :: GNU General Public License v2 (GPLv2)
Classifier: Operating System :: OS Independent
Classifier: Programming Language :: Python
Classifier: Programming Language :: Python :: 2.6
Classifier: Programming Language :: Python :: 2.7
Classifier: Topic :: Office/Business :: News/Diary
Classifier: Topic :: Software Development :: Libraries :: Python Modules
